{
    "C260001": {
        "event": "FC26 EA SPORTS",
        "team_override": [
            "harish"
        ],
        "reported": true,
        "event_started": true,
        "event_ended": true,
        "position": 1
    },
    "C260002": {
        "event": "Carrom (Men)",
        "reported": true,
        "event_started": false,
        "event_ended": false
    },
    "C260003": {
        "event": "IPL Auction",
        "team_override": [
            "Alan",
            "gowtham",
            "Shalin"
        ]
    }
}